botnettv.py
botnettv-0.0.1.dist-info/WHEEL
botnettv-0.0.1.dist-info/METADATA
botnettv-0.0.1.dist-info/RECORD
